{
  "index": 31,
  "text": "وَإِذَا تُتْلَىٰ عَلَيْهِمْ ءَايَـٰتُنَا قَالُوا۟ قَدْ سَمِعْنَا لَوْ نَشَآءُ لَقُلْنَا مِثْلَ هَـٰذَآ ۙ إِنْ هَـٰذَآ إِلَّآ أَسَـٰطِيرُ ٱلْأَوَّلِينَ",
  "translation": {
    "en.sahih": "And when Our verses are recited to them, they say, \"We have heard. If we willed, we could say [something] like this. This is not but legends of the former peoples.\"",
    "id.indonesian": "Dan apabila dibacakan kepada mereka ayat-ayat Kami, mereka berkata: \"Sesungguhnya kami telah mendengar (ayat-ayat yang seperti ini), kalau kami menhendaki niscaya kami dapat membacakan yang seperti ini, (Al Quran) ini tidak lain hanyalah dongeng-dongengan orang-orang purbakala\"."
  },
  "bismillah": null
}