{
  "index": 42,
  "text": "وَقَالَ لِلَّذِى ظَنَّ أَنَّهُۥ نَاجٍ مِّنْهُمَا ٱذْكُرْنِى عِندَ رَبِّكَ فَأَنسَىٰهُ ٱلشَّيْطَـٰنُ ذِكْرَ رَبِّهِۦ فَلَبِثَ فِى ٱلسِّجْنِ بِضْعَ سِنِينَ",
  "translation": {
    "en.sahih": "And he said to the one whom he knew would go free, \"Mention me before your master.\" But Satan made him forget the mention [to] his master, and Joseph remained in prison several years.",
    "id.indonesian": "Dan Yusuf berkata kepada orang yang diketahuinya akan selamat diantara mereka berdua: \"Terangkanlah keadaanku kepada tuanmu\". Maka syaitan menjadikan dia lupa menerangkan (keadaan Yusuf) kepada tuannya. Karena itu tetaplah dia (Yusuf) dalam penjara beberapa tahun lamanya."
  },
  "bismillah": null
}