{
  "index": 23,
  "text": "وَلَوْ عَلِمَ ٱللَّهُ فِيهِمْ خَيْرًا لَّأَسْمَعَهُمْ ۖ وَلَوْ أَسْمَعَهُمْ لَتَوَلَّوا۟ وَّهُم مُّعْرِضُونَ",
  "translation": {
    "en.sahih": "Had Allah known any good in them, He would have made them hear. And if He had made them hear, they would [still] have turned away, while they were refusing.",
    "id.indonesian": "Kalau sekiranya Allah mengetahui kebaikan ada pada mereka, tentulah Allah menjadikan mereka dapat mendengar. Dan jikalau Allah menjadikan mereka dapat mendengar, niscaya mereka pasti berpaling juga, sedang mereka memalingkan diri (dari apa yang mereka dengar itu)."
  },
  "bismillah": null
}