{
  "index": 125,
  "text": "وَأَمَّا ٱلَّذِينَ فِى قُلُوبِهِم مَّرَضٌ فَزَادَتْهُمْ رِجْسًا إِلَىٰ رِجْسِهِمْ وَمَاتُوا۟ وَهُمْ كَـٰفِرُونَ",
  "translation": {
    "en.sahih": "But as for those in whose hearts is disease, it has [only] increased them in evil [in addition] to their evil. And they will have died while they are disbelievers.",
    "id.indonesian": "Dan adapun orang-orang yang di dalam hati mereka ada penyakit, maka dengan surat itu bertambah kekafiran mereka, disamping kekafirannya (yang telah ada) dan mereka mati dalam keadaan kafir."
  },
  "bismillah": null
}