{
  "index": 5,
  "text": "مَن كَانَ يَرْجُوا۟ لِقَآءَ ٱللَّهِ فَإِنَّ أَجَلَ ٱللَّهِ لَـَٔاتٍ ۚ وَهُوَ ٱلسَّمِيعُ ٱلْعَلِيمُ",
  "translation": {
    "en.sahih": "Whoever should hope for the meeting with Allah - indeed, the term decreed by Allah is coming. And He is the Hearing, the Knowing.",
    "id.indonesian": "Barangsiapa yang mengharap pertemuan dengan Allah, maka sesungguhnya waktu (yang dijanjikan) Allah itu, pasti datang. Dan Dialah Yang Maha mendengar lagi Maha Mengetahui."
  },
  "bismillah": null
}